docopt_typed/__init__.py
docopt_typed/docopt_typed.py
docopt_typed-0.1.1.dist-info/METADATA
docopt_typed-0.1.1.dist-info/WHEEL
docopt_typed-0.1.1.dist-info/licenses/LICENSE
docopt_typed-0.1.1.dist-info/RECORD
