Metadata-Version: 2.4
Name: docopt-typed
Version: 0.1.1
Summary: A lightweight helper around docopt-ng adding automatic type conversion
Project-URL: Homepage, https://github.com/johnscillieri/docopt-typed
Project-URL: Repository, https://github.com/johnscillieri/docopt-typed
Project-URL: Issues, https://github.com/johnscillieri/os-normalizer/issues
Project-URL: Changelog, https://github.com/johnscillieri/docopt-typed
Author: John Scillieri
License: MIT License
License-File: LICENSE
Keywords: argparse,argument,docopt,parsing
Classifier: Development Status :: 4 - Beta
Classifier: Intended Audience :: Developers
Classifier: License :: OSI Approved :: MIT License
Classifier: Operating System :: OS Independent
Classifier: Programming Language :: Python
Classifier: Programming Language :: Python :: 3
Classifier: Programming Language :: Python :: 3 :: Only
Classifier: Programming Language :: Python :: 3.11
Classifier: Programming Language :: Python :: 3.12
Classifier: Programming Language :: Python :: 3.13
Classifier: Topic :: Software Development :: Libraries
Requires-Python: >=3.11
Requires-Dist: docopt-ng>=0.9.0
